{
  "date": "2026-07-18",
  "scored": 627,
  "penalized_count": 11,
  "total_points": 78.0,
  "density_per_1000": 124.40191387559808,
  "attribution_total": 174,
  "outlier_total": 11,
  "penalty_memo": {
    "total_deducted": 78,
    "by_expr": {
      "\\?$": {
        "count": 4,
        "deducted": 32,
        "근거": "물음표 종결 낚시"
      },
      "후폭풍": {
        "count": 1,
        "deducted": 8,
        "근거": "과장 프레이밍"
      },
      "(할까|일까|되나|아니냐|셈인가|것인가)\\??$": {
        "count": 2,
        "deducted": 16,
        "근거": "추측형 종결"
      },
      "무더기": {
        "count": 1,
        "deducted": 3,
        "근거": "과장 수량 묘사"
      },
      "발칵": {
        "count": 1,
        "deducted": 8,
        "근거": "감정 과장"
      },
      "(\\?!|!!+)": {
        "count": 1,
        "deducted": 3,
        "근거": "과도한 문장부호(감탄/의문 중복). …(말줄임표)는 한국 제목 표준 연결부호라 제외"
      },
      "논란이 커지고 있다": {
        "count": 1,
        "deducted": 8,
        "근거": "평가성 상투구"
      }
    },
    "by_source": {
      "매일경제": 16,
      "매일신문": 11,
      "SBS": 24,
      "연합뉴스": 8,
      "한겨레": 8,
      "전자신문": 3,
      "ZDNet Korea": 8
    }
  },
  "articles": [
    {
      "source": "매일경제",
      "category": "경제",
      "title": "이젠 정말 ‘헛꿈’ 안 꾼다”…한 달 새 청약통장 10만명 깬 이유는?",
      "link": "https://www.mk.co.kr/news/economy/12101222",
      "score": 92,
      "points": 8.0,
      "hits": [
        "\\?$"
      ],
      "attribution": 0,
      "outlier": true
    },
    {
      "source": "매일경제",
      "category": "경제",
      "title": "금리인상 후폭풍 … 고령층부터 타격",
      "link": "https://www.mk.co.kr/news/economy/12101110",
      "score": 92,
      "points": 8.0,
      "hits": [
        "후폭풍"
      ],
      "attribution": 0,
      "outlier": true
    },
    {
      "source": "매일신문",
      "category": "경제",
      "title": "[기준금리 인상] 치솟는 물가·집값, 부채 경고등…내년 상반기 年 3.25∼3.50%?",
      "link": "https://www.imaeil.com/page/view/2026071615314288387",
      "score": 92,
      "points": 8.0,
      "hits": [
        "\\?$"
      ],
      "attribution": 0,
      "outlier": true
    },
    {
      "source": "SBS",
      "category": "경제",
      "title": "한 달에 7조 원 흡수한 '삼전닉스' 레버리지… 보완 대책 통할까",
      "link": "https://news.sbs.co.kr/news/endPage.do?news_id=N1008662333",
      "score": 92,
      "points": 8.0,
      "hits": [
        "(할까|일까|되나|아니냐|셈인가|것인가)\\??$"
      ],
      "attribution": 0,
      "outlier": true
    },
    {
      "source": "SBS",
      "category": "경제",
      "title": "\"상품권 어떻게 쓰라고\" 폭발…이제 '휴지 조각'?",
      "link": "https://news.sbs.co.kr/news/endPage.do?news_id=N1008662024",
      "score": 92,
      "points": 8.0,
      "hits": [
        "\\?$"
      ],
      "attribution": 0,
      "outlier": true
    },
    {
      "source": "연합뉴스",
      "category": "사회",
      "title": "[샷!] 임산부 배지가 왜 중고시장에?",
      "link": "https://www.yna.co.kr/view/AKR20260715166600011",
      "score": 92,
      "points": 8.0,
      "hits": [
        "\\?$"
      ],
      "attribution": 0,
      "outlier": true
    },
    {
      "source": "매일신문",
      "category": "사회",
      "title": "경찰, 올공 집회 관련 구속영장 무더기 신청…'올다르크' 구속 기로에",
      "link": "https://www.imaeil.com/page/view/2026071621374476015",
      "score": 97,
      "points": 3.0,
      "hits": [
        "무더기"
      ],
      "attribution": 0,
      "outlier": true
    },
    {
      "source": "SBS",
      "category": "사회",
      "title": "\"우리 애 괜찮나\" 한국인만 2만여 명…전격 발표에 발칵",
      "link": "https://news.sbs.co.kr/news/endPage.do?news_id=N1008662623",
      "score": 92,
      "points": 8.0,
      "hits": [
        "발칵"
      ],
      "attribution": 0,
      "outlier": true
    },
    {
      "source": "한겨레",
      "category": "세계",
      "title": "일본 ‘국기 손괴죄’ 국회 통과…헌법 보장 ‘표현의 자유’ 침해되나",
      "link": "https://www.hani.co.kr/arti/international/international_general/1268767.html",
      "score": 92,
      "points": 8.0,
      "hits": [
        "(할까|일까|되나|아니냐|셈인가|것인가)\\??$"
      ],
      "attribution": 0,
      "outlier": true
    },
    {
      "source": "전자신문",
      "category": "IT/테크",
      "title": "방탄소년단 '아리랑' 메가 히트 덕?! 韓, 세계 3위 음악 수출국",
      "link": "https://www.etnews.com/20260717000041",
      "score": 97,
      "points": 3.0,
      "hits": [
        "(\\?!|!!+)"
      ],
      "attribution": 0,
      "outlier": true
    },
    {
      "source": "ZDNet Korea",
      "category": "IT/테크",
      "title": "기업 띄우기 전 주식부터 샀다…트럼프의 수상한 거래 타이밍 논란",
      "link": "https://zdnet.co.kr/view/?no=20260717143927",
      "score": 92,
      "points": 8.0,
      "hits": [
        "논란이 커지고 있다"
      ],
      "attribution": 2,
      "outlier": true
    }
  ]
}